[
    {
        "id": 0,
        "name": "Ulyana",
        "age": 18
    },
    {
        "id": 1,
        "name": "Sergey",
        "age": 21
    },
    {
        "id": 2,
        "name": "Dima",
        "age": 38
    },
    {
        "id": 3,
        "name": "Alice",
        "age": 41
    },
    {
        "id": 4,
        "name": "Dima",
        "age": 24
    },
    {
        "id": 5,
        "name": "Ulyana",
        "age": 43
    },
    {
        "id": 6,
        "name": "Sergey",
        "age": 32
    },
    {
        "id": 7,
        "name": "Ulyana",
        "age": 26
    },
    {
        "id": 8,
        "name": "Dima",
        "age": 28
    },
    {
        "id": 9,
        "name": "Alice",
        "age": 42
    },
    {
        "id": 10,
        "name": "Alice",
        "age": 21
    },
    {
        "id": 11,
        "name": "Dima",
        "age": 24
    },
    {
        "id": 12,
        "name": "Sergey",
        "age": 26
    },
    {
        "id": 13,
        "name": "Dima",
        "age": 43
    },
    {
        "id": 14,
        "name": "Ulyana",
        "age": 40
    },
    {
        "id": 15,
        "name": "Alice",
        "age": 42
    },
    {
        "id": 16,
        "name": "Sergey",
        "age": 22
    },
    {
        "id": 17,
        "name": "Ulyana",
        "age": 41
    },
    {
        "id": 18,
        "name": "Sergey",
        "age": 45
    },
    {
        "id": 19,
        "name": "Ulyana",
        "age": 43
    },
    {
        "id": 20,
        "name": "Olga",
        "age": 22
    },
    {
        "id": 21,
        "name": "Olga",
        "age": 37
    },
    {
        "id": 22,
        "name": "Ulyana",
        "age": 30
    },
    {
        "id": 23,
        "name": "Dima",
        "age": 26
    },
    {
        "id": 24,
        "name": "Dima",
        "age": 32
    },
    {
        "id": 25,
        "name": "Ulyana",
        "age": 29
    },
    {
        "id": 26,
        "name": "Sergey",
        "age": 45
    },
    {
        "id": 27,
        "name": "Dima",
        "age": 34
    },
    {
        "id": 28,
        "name": "Dima",
        "age": 29
    },
    {
        "id": 29,
        "name": "Olga",
        "age": 28
    },
    {
        "id": 30,
        "name": "Sergey",
        "age": 24
    },
    {
        "id": 31,
        "name": "Ulyana",
        "age": 27
    },
    {
        "id": 32,
        "name": "Dima",
        "age": 36
    },
    {
        "id": 33,
        "name": "Dima",
        "age": 26
    },
    {
        "id": 34,
        "name": "Sergey",
        "age": 30
    },
    {
        "id": 35,
        "name": "Dima",
        "age": 21
    },
    {
        "id": 36,
        "name": "Alice",
        "age": 43
    },
    {
        "id": 37,
        "name": "Olga",
        "age": 44
    },
    {
        "id": 38,
        "name": "Ulyana",
        "age": 33
    },
    {
        "id": 39,
        "name": "Dima",
        "age": 28
    },
    {
        "id": 40,
        "name": "Sergey",
        "age": 38
    },
    {
        "id": 41,
        "name": "Sergey",
        "age": 28
    },
    {
        "id": 42,
        "name": "Olga",
        "age": 42
    },
    {
        "id": 43,
        "name": "Ulyana",
        "age": 45
    },
    {
        "id": 44,
        "name": "Ulyana",
        "age": 33
    },
    {
        "id": 45,
        "name": "Ulyana",
        "age": 40
    },
    {
        "id": 46,
        "name": "Olga",
        "age": 26
    },
    {
        "id": 47,
        "name": "Dima",
        "age": 23
    },
    {
        "id": 48,
        "name": "Sergey",
        "age": 32
    },
    {
        "id": 49,
        "name": "Dima",
        "age": 29
    }
]